toolva/__init__.py
toolva/toolva.py
toolva/tasks/__init__.py
toolva/tasks/embeding.py
toolva/tasks/keyword_extraction.py
toolva/tasks/konlpy_mecab.py
toolva/tasks/named_entity_recognition.py
toolva/tasks/sentiments.py
toolva-1.9.2.dist-info/LICENSE
toolva-1.9.2.dist-info/METADATA
toolva-1.9.2.dist-info/WHEEL
toolva-1.9.2.dist-info/top_level.txt
toolva-1.9.2.dist-info/RECORD
