Metadata-Version: 2.1
Name: toolva
Version: 1.9.2
Summary: SosiAl Media Bigdata Analysis service by pcn
Home-page: http://git.pcnrns.kro.kr:9000/dwdoit22/toolva
Author: pcnrns
Author-email: dwdoit22@gmail.com
License: Apache-2.0
Classifier: Programming Language :: Python :: 3
Classifier: License :: OSI Approved :: Apache Software License
Classifier: Operating System :: OS Independent
Classifier: Topic :: Scientific/Engineering :: Artificial Intelligence
Requires-Python: >=3.8
License-File: LICENSE
Requires-Dist: typing
Requires-Dist: torch (==1.11.0)
Requires-Dist: tensorflow (==2.3.0)
Requires-Dist: konlpy (==0.5.2)
Requires-Dist: nltk (==3.7)
Requires-Dist: transformers (==4.15.0)
Requires-Dist: sentence-transformers (>=2.2.0)
Requires-Dist: keybert (==0.5.1)
Requires-Dist: nltk (>=3.5)
Requires-Dist: tweepy (==3.10.0)
